audio_feature_extractor/__init__.py
audio_feature_extractor/extractor.py
audio_feature_extractor/features/__init__.py
audio_feature_extractor/features/embedding.py
audio_feature_extractor/features/semantic.py
audio_feature_extractor/features/traditional.py
audio_feature_extractor/g2p/__init__.py
audio_feature_extractor-0.1.1.dist-info/METADATA
audio_feature_extractor-0.1.1.dist-info/WHEEL
audio_feature_extractor-0.1.1.dist-info/licenses/LICENSE
audio_feature_extractor-0.1.1.dist-info/RECORD
