Metadata-Version: 2.4
Name: audio-feature-extractor
Version: 0.1.1
Summary: a simple audio feature extraction tool
Project-URL: Homepage, https://github.com/Dongru1/audio_feature_extractor
Project-URL: Issues, https://github.com/Dongru1/audio_feature_extractor/issues
Author-email: drhan <handongrui1996@gmail.com>
License-File: LICENSE
Requires-Python: >=3.12
Requires-Dist: g2p-en>=2.1.0
Requires-Dist: g2pw>=0.1.1
Requires-Dist: librosa>=0.11.0
Requires-Dist: matplotlib>=3.10.7
Requires-Dist: numpy>=2.3.4
Requires-Dist: pandas>=2.3.3
Requires-Dist: pip>=25.2
Requires-Dist: praat-parselmouth>=0.4.6
Requires-Dist: speechbrain>=1.0.3
Requires-Dist: torch==2.6.0
Requires-Dist: torchaudio==2.6.0
Requires-Dist: torchvision>=0.19.1
Requires-Dist: transformers>=4.57.1
Requires-Dist: whisperx>=3.3.1
